Workbook

Sheet Raw Data
A1: Season | B1: Team | C1: Championship Position | D1: Constructors Points | E1: Wins | F1: Podiums | G1: Revenue (USD Millions) | H1: Team Value (USD Millions) | I1: Source | J1: Notes | K1: Revenue per Constructor Point (USD M) | L1: Points per $100M Revenue
A2: 2025 | B2: McLaren | C2: 1 | D2: 833 | E2: 14 | F2: 34 | G2: 614 | H2: 4400 | I2: Formula1.com and StatsF1 Forbes 2025 | J2: 2025 sporting results; 2024 revenue and 2025 estimated valuation | K2: =G2/D2 -> 0.73709484 | L2: =D2/G2*100 -> 135.66775
A3: 2025 | B3: Mercedes | C3: 2 | D3: 469 | E3: 2 | F3: 12 | G3: 799 | H3: 6000 | I3: Formula1.com and StatsF1 Forbes 2025 | J3: 2025 sporting results; 2024 revenue and 2025 estimated valuation | K3: =G3/D3 -> 1.7036247 | L3: =D3/G3*100 -> 58.698373
A4: 2025 | B4: Red Bull Racing | C4: 3 | D4: 451 | E4: 8 | F4: 15 | G4: 618 | H4: 4350 | I4: Formula1.com and StatsF1 Forbes 2025 | J4: 2025 sporting results; 2024 revenue and 2025 estimated valuation | K4: =G4/D4 -> 1.3702882 | L4: =D4/G4*100 -> 72.977346
A5: 2025 | B5: Ferrari | C5: 4 | D5: 398 | E5: 0 | F5: 7 | G5: 670 | H5: 6500 | I5: Formula1.com and StatsF1 Forbes 2025 | J5: 2025 sporting results; 2024 revenue and 2025 estimated valuation | K5: =G5/D5 -> 1.6834171 | L5: =D5/G5*100 -> 59.402985
A6: 2025 | B6: Williams | C6: 5 | D6: 137 | E6: 0 | F6: 2 | G6: 245 | H6: 2500 | I6: Formula1.com and StatsF1 Forbes 2025 | J6: 2025 sporting results; 2024 revenue and 2025 estimated valuation | K6: =G6/D6 -> 1.7883212 | L6: =D6/G6*100 -> 55.918367
A7: 2025 | B7: Racing Bulls | C7: 6 | D7: 92 | E7: 0 | F7: 1 | G7: 318 | H7: 2300 | I7: Formula1.com and StatsF1 Forbes 2025 | J7: 2025 sporting results; 2024 revenue and 2025 estimated valuation | K7: =G7/D7 -> 3.4565217 | L7: =D7/G7*100 -> 28.930818
A8: 2025 | B8: Aston Martin | C8: 7 | D8: 89 | E8: 0 | F8: 0 | G8: 353 | H8: 3200 | I8: Formula1.com and StatsF1 Forbes 2025 | J8: 2025 sporting results; 2024 revenue and 2025 estimated valuation | K8: =G8/D8 -> 3.9662921 | L8: =D8/G8*100 -> 25.212465
A9: 2025 | B9: Haas F1 Team | C9: 8 | D9: 79 | E9: 0 | F9: 0 | G9: 150 | H9: 1500 | I9: Formula1.com and StatsF1 Forbes 2025 | J9: 2025 sporting results; 2024 revenue and 2025 estimated valuation | K9: =G9/D9 -> 1.8987342 | L9: =D9/G9*100 -> 52.666667
A10: 2025 | B10: Kick Sauber | C10: 9 | D10: 70 | E10: 0 | F10: 1 | G10: 240 | H10: 2400 | I10: Formula1.com and StatsF1 Forbes 2025 | J10: 2025 sporting results; 2024 revenue and 2025 estimated valuation | K10: =G10/D10 -> 3.4285714 | L10: =D10/G10*100 -> 29.166667
A11: 2025 | B11: Alpine | C11: 10 | D11: 22 | E11: 0 | F11: 0 | G11: 300 | H11: 2450 | I11: Formula1.com and StatsF1 Forbes 2025 | J11: 2025 sporting results; 2024 revenue and 2025 estimated valuation | K11: =G11/D11 -> 13.636364 | L11: =D11/G11*100 -> 7.3333333

Sheet Calculations
A1: Metric | B1: Result
A2: Total Constructors Points | B2: =SUM('Raw Data'!D2:D11) -> 2640
A3: Average Points Per Team | B3: =AVERAGE('Raw Data'!D2:D11) -> 264
A4: Highest Team Points | B4: =MAX('Raw Data'!D2:D11) -> 833
A5: Total Race Wins | B5: =SUM('Raw Data'!E2:E11) -> 24
A6: Total Podiums | B6: =SUM('Raw Data'!F2:F11) -> 72

Sheet Chart Data
A1: Dashboard Chart Data
A2: Support ranges linked to Raw Data. Edit the Raw Data sheet, not this sheet.
A4: Team | B4: Constructors Points | D4: Team | E4: Wins | G4: Team | H4: Team Value (USD Millions) | J4: Team | K4: Revenue per Constructor Point | M4: Team | N4: Points per $100M Revenue
A5: ='Raw Data'!B2 -> McLaren | B5: ='Raw Data'!D2 -> 833 | D5: ='Raw Data'!B2 -> McLaren | E5: ='Raw Data'!E2 -> 14 | G5: ='Raw Data'!B2 -> McLaren | H5: ='Raw Data'!H2 -> 4400 | J5: ='Raw Data'!B2 -> McLaren | K5: ='Raw Data'!K2 -> 0.73709484 | M5: ='Raw Data'!B2 -> McLaren | N5: ='Raw Data'!L2 -> 135.66775
A6: ='Raw Data'!B3 -> Mercedes | B6: ='Raw Data'!D3 -> 469 | D6: ='Raw Data'!B3 -> Mercedes | E6: ='Raw Data'!E3 -> 2 | G6: ='Raw Data'!B3 -> Mercedes | H6: ='Raw Data'!H3 -> 6000 | J6: ='Raw Data'!B3 -> Mercedes | K6: ='Raw Data'!K3 -> 1.7036247 | M6: ='Raw Data'!B3 -> Mercedes | N6: ='Raw Data'!L3 -> 58.698373
A7: ='Raw Data'!B4 -> Red Bull Racing | B7: ='Raw Data'!D4 -> 451 | D7: ='Raw Data'!B4 -> Red Bull Racing | E7: ='Raw Data'!E4 -> 8 | G7: ='Raw Data'!B4 -> Red Bull Racing | H7: ='Raw Data'!H4 -> 4350 | J7: ='Raw Data'!B4 -> Red Bull Racing | K7: ='Raw Data'!K4 -> 1.3702882 | M7: ='Raw Data'!B4 -> Red Bull Racing | N7: ='Raw Data'!L4 -> 72.977346
A8: ='Raw Data'!B5 -> Ferrari | B8: ='Raw Data'!D5 -> 398 | D8: ='Raw Data'!B5 -> Ferrari | E8: ='Raw Data'!E5 -> 0 | G8: ='Raw Data'!B5 -> Ferrari | H8: ='Raw Data'!H5 -> 6500 | J8: ='Raw Data'!B5 -> Ferrari | K8: ='Raw Data'!K5 -> 1.6834171 | M8: ='Raw Data'!B5 -> Ferrari | N8: ='Raw Data'!L5 -> 59.402985
A9: ='Raw Data'!B6 -> Williams | B9: ='Raw Data'!D6 -> 137 | D9: ='Raw Data'!B6 -> Williams | E9: ='Raw Data'!E6 -> 0 | G9: ='Raw Data'!B6 -> Williams | H9: ='Raw Data'!H6 -> 2500 | J9: ='Raw Data'!B6 -> Williams | K9: ='Raw Data'!K6 -> 1.7883212 | M9: ='Raw Data'!B6 -> Williams | N9: ='Raw Data'!L6 -> 55.918367
A10: ='Raw Data'!B7 -> Racing Bulls | B10: ='Raw Data'!D7 -> 92 | D10: ='Raw Data'!B7 -> Racing Bulls | E10: ='Raw Data'!E7 -> 0 | G10: ='Raw Data'!B7 -> Racing Bulls | H10: ='Raw Data'!H7 -> 2300 | J10: ='Raw Data'!B7 -> Racing Bulls | K10: ='Raw Data'!K7 -> 3.4565217 | M10: ='Raw Data'!B7 -> Racing Bulls | N10: ='Raw Data'!L7 -> 28.930818
A11: ='Raw Data'!B8 -> Aston Martin | B11: ='Raw Data'!D8 -> 89 | D11: ='Raw Data'!B8 -> Aston Martin | E11: ='Raw Data'!E8 -> 0 | G11: ='Raw Data'!B8 -> Aston Martin | H11: ='Raw Data'!H8 -> 3200 | J11: ='Raw Data'!B8 -> Aston Martin | K11: ='Raw Data'!K8 -> 3.9662921 | M11: ='Raw Data'!B8 -> Aston Martin | N11: ='Raw Data'!L8 -> 25.212465
A12: ='Raw Data'!B9 -> Haas F1 Team | B12: ='Raw Data'!D9 -> 79 | D12: ='Raw Data'!B9 -> Haas F1 Team | E12: ='Raw Data'!E9 -> 0 | G12: ='Raw Data'!B9 -> Haas F1 Team | H12: ='Raw Data'!H9 -> 1500 | J12: ='Raw Data'!B9 -> Haas F1 Team | K12: ='Raw Data'!K9 -> 1.8987342 | M12: ='Raw Data'!B9 -> Haas F1 Team | N12: ='Raw Data'!L9 -> 52.666667
A13: ='Raw Data'!B10 -> Kick Sauber | B13: ='Raw Data'!D10 -> 70 | D13: ='Raw Data'!B10 -> Kick Sauber | E13: ='Raw Data'!E10 -> 0 | G13: ='Raw Data'!B10 -> Kick Sauber | H13: ='Raw Data'!H10 -> 2400 | J13: ='Raw Data'!B10 -> Kick Sauber | K13: ='Raw Data'!K10 -> 3.4285714 | M13: ='Raw Data'!B10 -> Kick Sauber | N13: ='Raw Data'!L10 -> 29.166667
A14: ='Raw Data'!B11 -> Alpine | B14: ='Raw Data'!D11 -> 22 | D14: ='Raw Data'!B11 -> Alpine | E14: ='Raw Data'!E11 -> 0 | G14: ='Raw Data'!B11 -> Alpine | H14: ='Raw Data'!H11 -> 2450 | J14: ='Raw Data'!B11 -> Alpine | K14: ='Raw Data'!K11 -> 13.636364 | M14: ='Raw Data'!B11 -> Alpine | N14: ='Raw Data'!L11 -> 7.3333333

Sheet Dashboard
A1: FORMULA 1 TEAM FINANCIAL PERFORMANCE DASHBOARD
A3: 2025 sporting results | 2024 revenue estimates | 2025 estimated team valuations
A5: CONSTRUCTORS’ CHAMPION | E5: MOST RACE WINS | I5: HIGHEST TEAM VALUATION | M5: BEST REVENUE EFFICIENCY
A6: McLaren | E6: McLaren — 14 | I6: Ferrari — $6.5B | M6: McLaren — 135.7 pts / $100M
A10: PERFORMANCE AND VALUATION ANALYSIS
A63: Interpretation note: Revenue is not the same as spending, profit, or investment. The efficiency measures compare 2024 revenue estimates with 2025 sporting results and should not be treated as profitability or ROI.

Sheet Executive Summary
A1: FORMULA 1 TEAM FINANCIAL PERFORMANCE ANALYSIS
A3: Executive Summary
A5: PROJECT OBJECTIVE
A6: This project examines the relationship between Formula 1 teams’ financial scale and on-track performance. It compares Constructors’ Championship points, race wins, estimated team valuations, and revenue-based efficiency metrics to identify which teams achieved the strongest sporting results relative to their reported revenue.
A9: KEY FINDINGS
A10: McLaren recorded the strongest sporting performance with 833 Constructors’ points and 14 race wins. It also produced approximately 135.7 points per $100 million of revenue, the highest revenue-efficiency result in the analysis. Ferrari had the highest estimated valuation at $6.5 billion, showing that team value also reflects brand history, commercial strength, and long-term appeal.
A14: WEAKEST PERFORMANCE
A15: Alpine scored only 22 points and produced approximately 7.3 points per $100 million of revenue, the lowest result among the teams analyzed. This indicates a large gap between the team’s revenue and its 2025 sporting performance. However, the calculation does not measure profit, actual spending, or return on investment.
A19: CONCLUSION
A20: The analysis suggests that higher revenue and team valuation do not automatically lead to better racing results. McLaren achieved the strongest performance relative to revenue, while Ferrari remained the most valuable team despite finishing fourth in the Constructors’ Championship. Formula 1 performance therefore depends on how effectively teams convert financial resources, personnel, engineering, and strategy into results.
A24: LIMITATIONS
A25: The sporting results are from the 2025 season, while the revenue figures represent 2024 operations and the team valuations are 2025 estimates. Revenue is not the same as spending, cost, profit, or investment. The calculations therefore compare team revenue with racing results, but they do not show how profitable each team was or how effectively it spent its money.

Sheet Sources
A1: Source Name | B1: Website Link | C1: Data Collected | D1: Season | E1: Date Accessed | F1: Reliability Notes
A2: Formula 1 | B2: https://www.formula1.com/en/results/2025/team | C2: Championship position and Constructors’ points | D2: 2025 | E2: 46233 | F2: Official Formula 1 source
A3: StatsF1 | B3: https://www.statsf1.com/en/2025/stats-victoire.aspx | C3: Wins by team | D3: 2025 | E3: 46233 | F3: Formula 1 statistics database
A4: StatsF1 | B4: https://www.statsf1.com/en/2025/stats-podium.aspx | C4: Podiums by team | D4: 2025 | E4: 46233 | F4: Formula 1 statistics database
A5: Forbes — Formula 1’s Most Valuable Teams 2025 by Brett Knight | B5: https://www.forbes.com/sites/brettknight/2025/11/20/formula-1s-most-valuable-teams-2025/ | C5: 2024 revenue estimates and 2025 estimated team valuations for all 10 Formula 1 teams | D5: 2024 revenue / 2025 valuations | E5: 46234 | F5: Forbes SportsMoney estimates from a reputable business publication; figures are estimates and are not audited official team financial statements
A6: Forbes Australia — From Marlboro to LVMH: How the Business of F1 Evolved Into a $21 Billion Giant | B6: https://www.forbes.com.au/covers/magazine/from-marlboro-to-lvmh-the-business-of-f1-has-never-been-richer/ | C6: Verification of the Forbes SportsMoney revenue and valuation figures used in the analysis | D6: 2024 revenue / 2025 valuations | E6: 46234 | F6: Forbes publication reproducing the complete Forbes SportsMoney table; used to verify the figures rather than as a separate independent estimate
